time_converter/__init__.py
time_converter_Piton007-0.1.dist-info/LICENSE
time_converter_Piton007-0.1.dist-info/METADATA
time_converter_Piton007-0.1.dist-info/WHEEL
time_converter_Piton007-0.1.dist-info/top_level.txt
time_converter_Piton007-0.1.dist-info/RECORD
