Metadata-Version: 2.1
Name: time-converter-Piton007
Version: 0.1
Summary: Time converter
Home-page: https://github.com/Piton007/time-converter
Author: Piton007
Author-email: josemowa45321@gmail.com
License: UNKNOWN
Platform: UNKNOWN
Classifier: Programming Language :: Python :: 3
Classifier: License :: OSI Approved :: MIT License
Classifier: Operating System :: OS Independent
Requires-Python: >=3.6
